[
  {
    "year": 2015,
    "form": "20-F",
    "filingDate": "2016-04-11",
    "reportDate": "2015-12-31",
    "accessionNumber": "0001193125-16-536225",
    "primaryDocument": "d138743d20f.htm",
    "secUrl": "https://www.sec.gov/Archives/edgar/data/1046179/000119312516536225/d138743d20f.htm",
    "extraction": {
      "confidence": 0.75,
      "method": "text_scored",
      "errors": [
        "anchor_missing",
        "early_position_penalty"
      ]
    }
  },
  {
    "year": 2016,
    "form": "20-F",
    "filingDate": "2017-04-13",
    "reportDate": "2016-12-31",
    "accessionNumber": "0001193125-17-122097",
    "primaryDocument": "d366455d20f.htm",
    "secUrl": "https://www.sec.gov/Archives/edgar/data/1046179/000119312517122097/d366455d20f.htm",
    "extraction": {
      "confidence": 0.75,
      "method": "text_scored",
      "errors": [
        "anchor_missing",
        "early_position_penalty"
      ]
    }
  },
  {
    "year": 2017,
    "form": "20-F",
    "filingDate": "2018-04-19",
    "reportDate": "2017-12-31",
    "accessionNumber": "0001193125-18-121866",
    "primaryDocument": "d459142d20f.htm",
    "secUrl": "https://www.sec.gov/Archives/edgar/data/1046179/000119312518121866/d459142d20f.htm",
    "extraction": {
      "confidence": 0.75,
      "method": "text_scored",
      "errors": [
        "anchor_missing",
        "early_position_penalty"
      ]
    }
  },
  {
    "year": 2018,
    "form": "20-F",
    "filingDate": "2019-04-17",
    "reportDate": "2018-12-31",
    "accessionNumber": "0001193125-19-108390",
    "primaryDocument": "d665387d20f.htm",
    "secUrl": "https://www.sec.gov/Archives/edgar/data/1046179/000119312519108390/d665387d20f.htm",
    "extraction": {
      "confidence": 0.75,
      "method": "text_scored",
      "errors": [
        "anchor_missing",
        "early_position_penalty"
      ]
    }
  },
  {
    "year": 2019,
    "form": "20-F",
    "filingDate": "2020-04-15",
    "reportDate": "2019-12-31",
    "accessionNumber": "0001193125-20-107579",
    "primaryDocument": "d831201d20f.htm",
    "secUrl": "https://www.sec.gov/Archives/edgar/data/1046179/000119312520107579/d831201d20f.htm",
    "extraction": {
      "confidence": 0.75,
      "method": "text_scored",
      "errors": [
        "anchor_missing",
        "early_position_penalty"
      ]
    }
  },
  {
    "year": 2020,
    "form": "20-F",
    "filingDate": "2021-04-16",
    "reportDate": "2020-12-31",
    "accessionNumber": "0001193125-21-118512",
    "primaryDocument": "d94821d20f.htm",
    "secUrl": "https://www.sec.gov/Archives/edgar/data/1046179/000119312521118512/d94821d20f.htm",
    "extraction": {
      "confidence": 0.75,
      "method": "text_scored",
      "errors": [
        "anchor_missing",
        "early_position_penalty"
      ]
    }
  },
  {
    "year": 2021,
    "form": "20-F",
    "filingDate": "2022-04-14",
    "reportDate": "2021-12-31",
    "accessionNumber": "0001193125-22-104891",
    "primaryDocument": "d204786d20f.htm",
    "secUrl": "https://www.sec.gov/Archives/edgar/data/1046179/000119312522104891/d204786d20f.htm",
    "extraction": {
      "confidence": 0.8999999999999999,
      "method": "text_scored",
      "errors": [
        "anchor_missing"
      ]
    }
  },
  {
    "year": 2022,
    "form": "20-F",
    "filingDate": "2023-04-20",
    "reportDate": "2022-12-31",
    "accessionNumber": "0001193125-23-107214",
    "primaryDocument": "d428519d20f.htm",
    "secUrl": "https://www.sec.gov/Archives/edgar/data/1046179/000119312523107214/d428519d20f.htm",
    "extraction": {
      "confidence": 0.95,
      "method": "text_scored",
      "errors": [
        "anchor_missing"
      ]
    }
  },
  {
    "year": 2023,
    "form": "20-F",
    "filingDate": "2024-04-18",
    "reportDate": "2023-12-31",
    "accessionNumber": "0001193125-24-099840",
    "primaryDocument": "d592628d20f.htm",
    "secUrl": "https://www.sec.gov/Archives/edgar/data/1046179/000119312524099840/d592628d20f.htm",
    "extraction": {
      "confidence": 0.8999999999999999,
      "method": "text_scored",
      "errors": [
        "anchor_missing"
      ]
    }
  },
  {
    "year": 2024,
    "form": "20-F",
    "filingDate": "2025-04-17",
    "reportDate": "2024-12-31",
    "accessionNumber": "0001193125-25-083423",
    "primaryDocument": "d896993d20f.htm",
    "secUrl": "https://www.sec.gov/Archives/edgar/data/1046179/000119312525083423/d896993d20f.htm",
    "extraction": {
      "confidence": 0.8999999999999999,
      "method": "text_scored",
      "errors": [
        "anchor_missing"
      ]
    }
  }
]