{
  "section": "10k_item1a",
  "yearPairs": [
    {
      "from": 2022,
      "to": 2023,
      "topRisers": [
        {
          "term": "ability",
          "score": 0.0,
          "z": 0.0,
          "countPrev": 1,
          "countCurr": 1,
          "per10kPrev": 90.09,
          "per10kCurr": 90.09,
          "deltaPer10k": 0.0,
          "distinctive": false
        },
        {
          "term": "activity",
          "score": 0.0,
          "z": 0.0,
          "countPrev": 1,
          "countCurr": 1,
          "per10kPrev": 90.09,
          "per10kCurr": 90.09,
          "deltaPer10k": 0.0,
          "distinctive": false
        },
        {
          "term": "adjustments",
          "score": 0.0,
          "z": 0.0,
          "countPrev": 1,
          "countCurr": 1,
          "per10kPrev": 90.09,
          "per10kCurr": 90.09,
          "deltaPer10k": 0.0,
          "distinctive": false
        },
        {
          "term": "affect",
          "score": 0.0,
          "z": 0.0,
          "countPrev": 1,
          "countCurr": 1,
          "per10kPrev": 90.09,
          "per10kCurr": 90.09,
          "deltaPer10k": 0.0,
          "distinctive": false
        },
        {
          "term": "anticipate",
          "score": 0.0,
          "z": 0.0,
          "countPrev": 1,
          "countCurr": 1,
          "per10kPrev": 90.09,
          "per10kCurr": 90.09,
          "deltaPer10k": 0.0,
          "distinctive": false
        },
        {
          "term": "availability",
          "score": 0.0,
          "z": 0.0,
          "countPrev": 1,
          "countCurr": 1,
          "per10kPrev": 90.09,
          "per10kCurr": 90.09,
          "deltaPer10k": 0.0,
          "distinctive": false
        },
        {
          "term": "breaches",
          "score": 0.0,
          "z": 0.0,
          "countPrev": 1,
          "countCurr": 1,
          "per10kPrev": 90.09,
          "per10kCurr": 90.09,
          "deltaPer10k": 0.0,
          "distinctive": false
        },
        {
          "term": "business",
          "score": 0.0,
          "z": 0.0,
          "countPrev": 1,
          "countCurr": 1,
          "per10kPrev": 90.09,
          "per10kCurr": 90.09,
          "deltaPer10k": 0.0,
          "distinctive": false
        },
        {
          "term": "chain",
          "score": 0.0,
          "z": 0.0,
          "countPrev": 1,
          "countCurr": 1,
          "per10kPrev": 90.09,
          "per10kCurr": 90.09,
          "deltaPer10k": 0.0,
          "distinctive": false
        },
        {
          "term": "changes",
          "score": 0.0,
          "z": 0.0,
          "countPrev": 3,
          "countCurr": 3,
          "per10kPrev": 270.27,
          "per10kCurr": 270.27,
          "deltaPer10k": 0.0,
          "distinctive": false
        },
        {
          "term": "competitive",
          "score": 0.0,
          "z": 0.0,
          "countPrev": 1,
          "countCurr": 1,
          "per10kPrev": 90.09,
          "per10kCurr": 90.09,
          "deltaPer10k": 0.0,
          "distinctive": false
        },
        {
          "term": "complex",
          "score": 0.0,
          "z": 0.0,
          "countPrev": 1,
          "countCurr": 1,
          "per10kPrev": 90.09,
          "per10kCurr": 90.09,
          "deltaPer10k": 0.0,
          "distinctive": false
        },
        {
          "term": "components",
          "score": 0.0,
          "z": 0.0,
          "countPrev": 2,
          "countCurr": 2,
          "per10kPrev": 180.18,
          "per10kCurr": 180.18,
          "deltaPer10k": 0.0,
          "distinctive": false
        },
        {
          "term": "constraints",
          "score": 0.0,
          "z": 0.0,
          "countPrev": 1,
          "countCurr": 1,
          "per10kPrev": 90.09,
          "per10kCurr": 90.09,
          "deltaPer10k": 0.0,
          "distinctive": false
        },
        {
          "term": "costs",
          "score": 0.0,
          "z": 0.0,
          "countPrev": 2,
          "countCurr": 2,
          "per10kPrev": 180.18,
          "per10kCurr": 180.18,
          "deltaPer10k": 0.0,
          "distinctive": false
        }
      ],
      "topFallers": [
        {
          "term": "ability",
          "score": 0.0,
          "z": 0.0,
          "countPrev": 1,
          "countCurr": 1,
          "per10kPrev": 90.09,
          "per10kCurr": 90.09,
          "deltaPer10k": 0.0,
          "distinctive": false
        },
        {
          "term": "activity",
          "score": 0.0,
          "z": 0.0,
          "countPrev": 1,
          "countCurr": 1,
          "per10kPrev": 90.09,
          "per10kCurr": 90.09,
          "deltaPer10k": 0.0,
          "distinctive": false
        },
        {
          "term": "adjustments",
          "score": 0.0,
          "z": 0.0,
          "countPrev": 1,
          "countCurr": 1,
          "per10kPrev": 90.09,
          "per10kCurr": 90.09,
          "deltaPer10k": 0.0,
          "distinctive": false
        },
        {
          "term": "affect",
          "score": 0.0,
          "z": 0.0,
          "countPrev": 1,
          "countCurr": 1,
          "per10kPrev": 90.09,
          "per10kCurr": 90.09,
          "deltaPer10k": 0.0,
          "distinctive": false
        },
        {
          "term": "anticipate",
          "score": 0.0,
          "z": 0.0,
          "countPrev": 1,
          "countCurr": 1,
          "per10kPrev": 90.09,
          "per10kCurr": 90.09,
          "deltaPer10k": 0.0,
          "distinctive": false
        },
        {
          "term": "availability",
          "score": 0.0,
          "z": 0.0,
          "countPrev": 1,
          "countCurr": 1,
          "per10kPrev": 90.09,
          "per10kCurr": 90.09,
          "deltaPer10k": 0.0,
          "distinctive": false
        },
        {
          "term": "breaches",
          "score": 0.0,
          "z": 0.0,
          "countPrev": 1,
          "countCurr": 1,
          "per10kPrev": 90.09,
          "per10kCurr": 90.09,
          "deltaPer10k": 0.0,
          "distinctive": false
        },
        {
          "term": "business",
          "score": 0.0,
          "z": 0.0,
          "countPrev": 1,
          "countCurr": 1,
          "per10kPrev": 90.09,
          "per10kCurr": 90.09,
          "deltaPer10k": 0.0,
          "distinctive": false
        },
        {
          "term": "chain",
          "score": 0.0,
          "z": 0.0,
          "countPrev": 1,
          "countCurr": 1,
          "per10kPrev": 90.09,
          "per10kCurr": 90.09,
          "deltaPer10k": 0.0,
          "distinctive": false
        },
        {
          "term": "changes",
          "score": 0.0,
          "z": 0.0,
          "countPrev": 3,
          "countCurr": 3,
          "per10kPrev": 270.27,
          "per10kCurr": 270.27,
          "deltaPer10k": 0.0,
          "distinctive": false
        },
        {
          "term": "competitive",
          "score": 0.0,
          "z": 0.0,
          "countPrev": 1,
          "countCurr": 1,
          "per10kPrev": 90.09,
          "per10kCurr": 90.09,
          "deltaPer10k": 0.0,
          "distinctive": false
        },
        {
          "term": "complex",
          "score": 0.0,
          "z": 0.0,
          "countPrev": 1,
          "countCurr": 1,
          "per10kPrev": 90.09,
          "per10kCurr": 90.09,
          "deltaPer10k": 0.0,
          "distinctive": false
        },
        {
          "term": "components",
          "score": 0.0,
          "z": 0.0,
          "countPrev": 2,
          "countCurr": 2,
          "per10kPrev": 180.18,
          "per10kCurr": 180.18,
          "deltaPer10k": 0.0,
          "distinctive": false
        },
        {
          "term": "constraints",
          "score": 0.0,
          "z": 0.0,
          "countPrev": 1,
          "countCurr": 1,
          "per10kPrev": 90.09,
          "per10kCurr": 90.09,
          "deltaPer10k": 0.0,
          "distinctive": false
        },
        {
          "term": "costs",
          "score": 0.0,
          "z": 0.0,
          "countPrev": 2,
          "countCurr": 2,
          "per10kPrev": 180.18,
          "per10kCurr": 180.18,
          "deltaPer10k": 0.0,
          "distinctive": false
        }
      ],
      "summary": "Adds emphasis on ability, activity, adjustments; de-emphasizes ability, activity, adjustments."
    },
    {
      "from": 2023,
      "to": 2024,
      "topRisers": [
        {
          "term": "ability",
          "score": 0.0,
          "z": 0.0,
          "countPrev": 1,
          "countCurr": 1,
          "per10kPrev": 90.09,
          "per10kCurr": 90.09,
          "deltaPer10k": 0.0,
          "distinctive": false
        },
        {
          "term": "activity",
          "score": 0.0,
          "z": 0.0,
          "countPrev": 1,
          "countCurr": 1,
          "per10kPrev": 90.09,
          "per10kCurr": 90.09,
          "deltaPer10k": 0.0,
          "distinctive": false
        },
        {
          "term": "adjustments",
          "score": 0.0,
          "z": 0.0,
          "countPrev": 1,
          "countCurr": 1,
          "per10kPrev": 90.09,
          "per10kCurr": 90.09,
          "deltaPer10k": 0.0,
          "distinctive": false
        },
        {
          "term": "affect",
          "score": 0.0,
          "z": 0.0,
          "countPrev": 1,
          "countCurr": 1,
          "per10kPrev": 90.09,
          "per10kCurr": 90.09,
          "deltaPer10k": 0.0,
          "distinctive": false
        },
        {
          "term": "anticipate",
          "score": 0.0,
          "z": 0.0,
          "countPrev": 1,
          "countCurr": 1,
          "per10kPrev": 90.09,
          "per10kCurr": 90.09,
          "deltaPer10k": 0.0,
          "distinctive": false
        },
        {
          "term": "availability",
          "score": 0.0,
          "z": 0.0,
          "countPrev": 1,
          "countCurr": 1,
          "per10kPrev": 90.09,
          "per10kCurr": 90.09,
          "deltaPer10k": 0.0,
          "distinctive": false
        },
        {
          "term": "breaches",
          "score": 0.0,
          "z": 0.0,
          "countPrev": 1,
          "countCurr": 1,
          "per10kPrev": 90.09,
          "per10kCurr": 90.09,
          "deltaPer10k": 0.0,
          "distinctive": false
        },
        {
          "term": "business",
          "score": 0.0,
          "z": 0.0,
          "countPrev": 1,
          "countCurr": 1,
          "per10kPrev": 90.09,
          "per10kCurr": 90.09,
          "deltaPer10k": 0.0,
          "distinctive": false
        },
        {
          "term": "chain",
          "score": 0.0,
          "z": 0.0,
          "countPrev": 1,
          "countCurr": 1,
          "per10kPrev": 90.09,
          "per10kCurr": 90.09,
          "deltaPer10k": 0.0,
          "distinctive": false
        },
        {
          "term": "changes",
          "score": 0.0,
          "z": 0.0,
          "countPrev": 3,
          "countCurr": 3,
          "per10kPrev": 270.27,
          "per10kCurr": 270.27,
          "deltaPer10k": 0.0,
          "distinctive": false
        },
        {
          "term": "competitive",
          "score": 0.0,
          "z": 0.0,
          "countPrev": 1,
          "countCurr": 1,
          "per10kPrev": 90.09,
          "per10kCurr": 90.09,
          "deltaPer10k": 0.0,
          "distinctive": false
        },
        {
          "term": "complex",
          "score": 0.0,
          "z": 0.0,
          "countPrev": 1,
          "countCurr": 1,
          "per10kPrev": 90.09,
          "per10kCurr": 90.09,
          "deltaPer10k": 0.0,
          "distinctive": false
        },
        {
          "term": "components",
          "score": 0.0,
          "z": 0.0,
          "countPrev": 2,
          "countCurr": 2,
          "per10kPrev": 180.18,
          "per10kCurr": 180.18,
          "deltaPer10k": 0.0,
          "distinctive": false
        },
        {
          "term": "constraints",
          "score": 0.0,
          "z": 0.0,
          "countPrev": 1,
          "countCurr": 1,
          "per10kPrev": 90.09,
          "per10kCurr": 90.09,
          "deltaPer10k": 0.0,
          "distinctive": false
        },
        {
          "term": "costs",
          "score": 0.0,
          "z": 0.0,
          "countPrev": 2,
          "countCurr": 2,
          "per10kPrev": 180.18,
          "per10kCurr": 180.18,
          "deltaPer10k": 0.0,
          "distinctive": false
        }
      ],
      "topFallers": [
        {
          "term": "ability",
          "score": 0.0,
          "z": 0.0,
          "countPrev": 1,
          "countCurr": 1,
          "per10kPrev": 90.09,
          "per10kCurr": 90.09,
          "deltaPer10k": 0.0,
          "distinctive": false
        },
        {
          "term": "activity",
          "score": 0.0,
          "z": 0.0,
          "countPrev": 1,
          "countCurr": 1,
          "per10kPrev": 90.09,
          "per10kCurr": 90.09,
          "deltaPer10k": 0.0,
          "distinctive": false
        },
        {
          "term": "adjustments",
          "score": 0.0,
          "z": 0.0,
          "countPrev": 1,
          "countCurr": 1,
          "per10kPrev": 90.09,
          "per10kCurr": 90.09,
          "deltaPer10k": 0.0,
          "distinctive": false
        },
        {
          "term": "affect",
          "score": 0.0,
          "z": 0.0,
          "countPrev": 1,
          "countCurr": 1,
          "per10kPrev": 90.09,
          "per10kCurr": 90.09,
          "deltaPer10k": 0.0,
          "distinctive": false
        },
        {
          "term": "anticipate",
          "score": 0.0,
          "z": 0.0,
          "countPrev": 1,
          "countCurr": 1,
          "per10kPrev": 90.09,
          "per10kCurr": 90.09,
          "deltaPer10k": 0.0,
          "distinctive": false
        },
        {
          "term": "availability",
          "score": 0.0,
          "z": 0.0,
          "countPrev": 1,
          "countCurr": 1,
          "per10kPrev": 90.09,
          "per10kCurr": 90.09,
          "deltaPer10k": 0.0,
          "distinctive": false
        },
        {
          "term": "breaches",
          "score": 0.0,
          "z": 0.0,
          "countPrev": 1,
          "countCurr": 1,
          "per10kPrev": 90.09,
          "per10kCurr": 90.09,
          "deltaPer10k": 0.0,
          "distinctive": false
        },
        {
          "term": "business",
          "score": 0.0,
          "z": 0.0,
          "countPrev": 1,
          "countCurr": 1,
          "per10kPrev": 90.09,
          "per10kCurr": 90.09,
          "deltaPer10k": 0.0,
          "distinctive": false
        },
        {
          "term": "chain",
          "score": 0.0,
          "z": 0.0,
          "countPrev": 1,
          "countCurr": 1,
          "per10kPrev": 90.09,
          "per10kCurr": 90.09,
          "deltaPer10k": 0.0,
          "distinctive": false
        },
        {
          "term": "changes",
          "score": 0.0,
          "z": 0.0,
          "countPrev": 3,
          "countCurr": 3,
          "per10kPrev": 270.27,
          "per10kCurr": 270.27,
          "deltaPer10k": 0.0,
          "distinctive": false
        },
        {
          "term": "competitive",
          "score": 0.0,
          "z": 0.0,
          "countPrev": 1,
          "countCurr": 1,
          "per10kPrev": 90.09,
          "per10kCurr": 90.09,
          "deltaPer10k": 0.0,
          "distinctive": false
        },
        {
          "term": "complex",
          "score": 0.0,
          "z": 0.0,
          "countPrev": 1,
          "countCurr": 1,
          "per10kPrev": 90.09,
          "per10kCurr": 90.09,
          "deltaPer10k": 0.0,
          "distinctive": false
        },
        {
          "term": "components",
          "score": 0.0,
          "z": 0.0,
          "countPrev": 2,
          "countCurr": 2,
          "per10kPrev": 180.18,
          "per10kCurr": 180.18,
          "deltaPer10k": 0.0,
          "distinctive": false
        },
        {
          "term": "constraints",
          "score": 0.0,
          "z": 0.0,
          "countPrev": 1,
          "countCurr": 1,
          "per10kPrev": 90.09,
          "per10kCurr": 90.09,
          "deltaPer10k": 0.0,
          "distinctive": false
        },
        {
          "term": "costs",
          "score": 0.0,
          "z": 0.0,
          "countPrev": 2,
          "countCurr": 2,
          "per10kPrev": 180.18,
          "per10kCurr": 180.18,
          "deltaPer10k": 0.0,
          "distinctive": false
        }
      ],
      "summary": "Adds emphasis on ability, activity, adjustments; de-emphasizes ability, activity, adjustments."
    }
  ]
}