[
  {
    "year": 2016,
    "form": "10-K",
    "filingDate": "2016-08-16",
    "reportDate": "2016-06-30",
    "accessionNumber": "0001206774-16-006893",
    "primaryDocument": "clorox3118951_1-10k.htm",
    "secUrl": "https://www.sec.gov/Archives/edgar/data/21076/000120677416006893/clorox3118951_1-10k.htm",
    "extraction": {
      "confidence": 0.1,
      "method": "text_scored",
      "errors": [
        "anchor_missing",
        "length_out_of_band",
        "early_position_penalty",
        "low_confidence_item1a"
      ]
    }
  },
  {
    "year": 2017,
    "form": "10-K",
    "filingDate": "2017-08-15",
    "reportDate": "2017-06-30",
    "accessionNumber": "0001628280-17-008700",
    "primaryDocument": "fy17clx10k.htm",
    "secUrl": "https://www.sec.gov/Archives/edgar/data/21076/000162828017008700/fy17clx10k.htm",
    "extraction": {
      "confidence": 0.1,
      "method": "text_scored",
      "errors": [
        "anchor_missing",
        "length_out_of_band",
        "early_position_penalty",
        "low_confidence_item1a"
      ]
    }
  },
  {
    "year": 2018,
    "form": "10-K",
    "filingDate": "2018-08-14",
    "reportDate": "2018-06-30",
    "accessionNumber": "0000021076-18-000011",
    "primaryDocument": "fy18clx10k.htm",
    "secUrl": "https://www.sec.gov/Archives/edgar/data/21076/000002107618000011/fy18clx10k.htm",
    "extraction": {
      "confidence": 0.1,
      "method": "text_scored",
      "errors": [
        "anchor_missing",
        "length_out_of_band",
        "early_position_penalty",
        "low_confidence_item1a"
      ]
    }
  },
  {
    "year": 2019,
    "form": "10-K",
    "filingDate": "2019-08-14",
    "reportDate": "2019-06-30",
    "accessionNumber": "0000021076-19-000012",
    "primaryDocument": "fy19clx10k.htm",
    "secUrl": "https://www.sec.gov/Archives/edgar/data/21076/000002107619000012/fy19clx10k.htm",
    "extraction": {
      "confidence": 0.25,
      "method": "text_scored",
      "errors": [
        "anchor_missing",
        "length_out_of_band",
        "low_confidence_item1a"
      ]
    }
  },
  {
    "year": 2020,
    "form": "10-K",
    "filingDate": "2020-08-13",
    "reportDate": "2020-06-30",
    "accessionNumber": "0000021076-20-000016",
    "primaryDocument": "clx-20200630.htm",
    "secUrl": "https://www.sec.gov/Archives/edgar/data/21076/000002107620000016/clx-20200630.htm",
    "extraction": {
      "confidence": 0.25,
      "method": "text_scored",
      "errors": [
        "anchor_missing",
        "length_out_of_band",
        "low_confidence_item1a"
      ]
    }
  },
  {
    "year": 2021,
    "form": "10-K",
    "filingDate": "2021-08-10",
    "reportDate": "2021-06-30",
    "accessionNumber": "0000021076-21-000016",
    "primaryDocument": "clx-20210630.htm",
    "secUrl": "https://www.sec.gov/Archives/edgar/data/21076/000002107621000016/clx-20210630.htm",
    "extraction": {
      "confidence": 0.25,
      "method": "text_scored",
      "errors": [
        "anchor_missing",
        "length_out_of_band",
        "low_confidence_item1a"
      ]
    }
  },
  {
    "year": 2022,
    "form": "10-K",
    "filingDate": "2022-08-10",
    "reportDate": "2022-06-30",
    "accessionNumber": "0000021076-22-000026",
    "primaryDocument": "clx-20220630.htm",
    "secUrl": "https://www.sec.gov/Archives/edgar/data/21076/000002107622000026/clx-20220630.htm",
    "extraction": {
      "confidence": 0.25,
      "method": "text_scored",
      "errors": [
        "anchor_missing",
        "length_out_of_band",
        "low_confidence_item1a"
      ]
    }
  },
  {
    "year": 2023,
    "form": "10-K",
    "filingDate": "2023-08-10",
    "reportDate": "2023-06-30",
    "accessionNumber": "0000021076-23-000037",
    "primaryDocument": "clx-20230630.htm",
    "secUrl": "https://www.sec.gov/Archives/edgar/data/21076/000002107623000037/clx-20230630.htm",
    "extraction": {
      "confidence": 0.25,
      "method": "text_scored",
      "errors": [
        "anchor_missing",
        "length_out_of_band",
        "low_confidence_item1a"
      ]
    }
  },
  {
    "year": 2024,
    "form": "10-K",
    "filingDate": "2024-08-08",
    "reportDate": "2024-06-30",
    "accessionNumber": "0000021076-24-000030",
    "primaryDocument": "clx-20240630.htm",
    "secUrl": "https://www.sec.gov/Archives/edgar/data/21076/000002107624000030/clx-20240630.htm",
    "extraction": {
      "confidence": 0.25,
      "method": "text_scored",
      "errors": [
        "anchor_missing",
        "length_out_of_band",
        "low_confidence_item1a"
      ]
    }
  },
  {
    "year": 2025,
    "form": "10-K",
    "filingDate": "2025-08-08",
    "reportDate": "2025-06-30",
    "accessionNumber": "0000021076-25-000039",
    "primaryDocument": "clx-20250630.htm",
    "secUrl": "https://www.sec.gov/Archives/edgar/data/21076/000002107625000039/clx-20250630.htm",
    "extraction": {
      "confidence": 0.25,
      "method": "text_scored",
      "errors": [
        "anchor_missing",
        "length_out_of_band",
        "low_confidence_item1a"
      ]
    }
  }
]